upi/__init__.py
upi/config.py
upi/pay/__init__.py
upi/pay/wxpay.py
upi/util/__init__.py
upi/util/log.py
upi/util/tool.py
upi-0.1.0.dist-info/METADATA
upi-0.1.0.dist-info/WHEEL
upi-0.1.0.dist-info/top_level.txt
upi-0.1.0.dist-info/RECORD
