Metadata-Version: 2.1
Name: upi
Version: 0.1.0
Summary: pay sdk
Home-page: https://github.com/linqigu/upi
Author: linqigu
Author-email: linqigu@163.com
License: MIT Licence
Download-URL: https://github.com/linqigu/upi
Keywords: upi,pay,wxPay
Platform: any
Classifier: Programming Language :: Python :: 3
Classifier: License :: OSI Approved :: MIT License
Requires-Python: >=3.6
Requires-Dist: requests
Requires-Dist: bs4
Requires-Dist: lxml
